MANIFEST.in
README.md
pyproject.toml
setup.py
mdfs/__init__.py
mdfs/c.py
mdfs/compute_max_ig.py
mdfs/compute_tuples.py
mdfs/fit_p_value.py
mdfs/internal_common.py
mdfs/run.py
mdfs/utils.py
mdfs.egg-info/PKG-INFO
mdfs.egg-info/SOURCES.txt
mdfs.egg-info/dependency_links.txt
mdfs.egg-info/requires.txt
mdfs.egg-info/top_level.txt
shared/interface/common.h
shared/interface/compute_max_ig.cpp
shared/interface/compute_tuples.cpp
shared/interface/discretize.cpp
shared/interface/fit_p_value.cpp
shared/interface/free_helpers.cpp
shared/interface/gen_contrast_variables.cpp
shared/interface/get_suggested_range.cpp
shared/interface/get_suggested_range.h
shared/src/cpu/common.cpp
shared/src/cpu/common.h
shared/src/cpu/dataset.h
shared/src/cpu/discretize.cpp
shared/src/cpu/discretize.h
shared/src/cpu/entropy.h
shared/src/cpu/mdfs.h
shared/src/cpu/mdfs_count_counters.h
shared/src/cpu/mdfs_cpu_kernel.h
shared/src/cpu/mdfs_reduce_counters.h