Metadata-Version: 2.1
Name: mdfs
Version: 1.5.0
Summary: A library for MultiDimensional Feature Selection (MDFS)
Author-email: Radosław Piliszek <r.piliszek@uwb.edu.pl>
Maintainer-email: Radosław Piliszek <r.piliszek@uwb.edu.pl>
Project-URL: homepage, https://www.mdfs.it/
Project-URL: changelog, https://mdfs.it/CHANGELOG
Keywords: feature selection,classification,machine learning,information theory
Classifier: Development Status :: 5 - Production/Stable
Classifier: Intended Audience :: Developers
Classifier: Intended Audience :: Science/Research
Classifier: Topic :: Scientific/Engineering :: Artificial Intelligence
Classifier: License :: OSI Approved :: GNU General Public License v3 (GPLv3)
Classifier: Programming Language :: Python :: 3.9
Classifier: Programming Language :: Python :: 3.10
Classifier: Programming Language :: Python :: 3.11
